rust_read_extraction-0.1.0.dist-info/METADATA
rust_read_extraction-0.1.0.dist-info/WHEEL
rust_read_extraction/__init__.py
rust_read_extraction/rust_read_extraction.abi3.so
rust_read_extraction-0.1.0.dist-info/RECORD
