Metadata-Version: 2.4
Name: rust_read_extraction
Version: 0.1.0
Classifier: Development Status :: 4 - Beta
Classifier: Intended Audience :: Science/Research
Classifier: License :: OSI Approved :: MIT License
Classifier: Programming Language :: Python :: 3
Classifier: Programming Language :: Python :: 3.8
Classifier: Programming Language :: Python :: 3.9
Classifier: Programming Language :: Python :: 3.10
Classifier: Programming Language :: Python :: 3.11
Classifier: Programming Language :: Python :: 3.12
Classifier: Programming Language :: Rust
Classifier: Topic :: Scientific/Engineering :: Bio-Informatics
Summary: Fast BAM to FASTQ conversion with region filtering for SDrecall
Keywords: bioinformatics,bam,fastq,ngs,genomics
Author: Xingtian Yang <yangyxt@hku.hk>
Author-email: Xingtian Yang <yangyxt@hku.hk>
License: MIT
Requires-Python: >=3.8
Project-URL: Homepage, https://github.com/snakesch/SDrecall
Project-URL: Repository, https://github.com/snakesch/SDrecall
